topsis/__init__.py
topsis/__main__.py
TOPSIS_Brahaminder_101803725-1.0.0.dist-info/LICENSE.txt
TOPSIS_Brahaminder_101803725-1.0.0.dist-info/METADATA
TOPSIS_Brahaminder_101803725-1.0.0.dist-info/WHEEL
TOPSIS_Brahaminder_101803725-1.0.0.dist-info/entry_points.txt
TOPSIS_Brahaminder_101803725-1.0.0.dist-info/top_level.txt
TOPSIS_Brahaminder_101803725-1.0.0.dist-info/RECORD
