Metadata-Version: 2.1
Name: TOPSIS-Brahaminder-101803725
Version: 1.0.0
Summary: Implementation of TOPSIS
Home-page: UNKNOWN
Author: Brahaminder Garg
License: MIT
Platform: UNKNOWN
Classifier: License :: OSI Approved :: MIT License
Classifier: Programming Language :: Python :: 3.6
Classifier: Programming Language :: Python :: 3.7
Classifier: Programming Language :: Python :: 3.8
Requires-Dist: pandas
